filestream_y/FileStream_y.py
filestream_y/__init__.py
filestream_y/filetype_map.py
filestream_y-0.1.9.dist-info/METADATA
filestream_y-0.1.9.dist-info/WHEEL
filestream_y-0.1.9.dist-info/RECORD
